genMD_badges/__init__.py
genMD_badges/__version__.py
genMD_badges/core.py
genMD_badges-0.1.2.dist-info/LICENSE
genMD_badges-0.1.2.dist-info/METADATA
genMD_badges-0.1.2.dist-info/WHEEL
genMD_badges-0.1.2.dist-info/top_level.txt
genMD_badges-0.1.2.dist-info/RECORD
