Metadata-Version: 2.1
Name: genMD-badges
Version: 0.1.2
Summary: Generate hashCheck html file of local .so files.
Home-page: https://github.com/zhaozl1123/genMD_badges
Author: zhaozl1123
Author-email: zhaozl1123@qq.com
License: MIT
Platform: UNKNOWN
Classifier: License :: OSI Approved :: MIT License
Classifier: Programming Language :: Python
Classifier: Programming Language :: Python :: 3
Classifier: Programming Language :: Python :: 3.6
Classifier: Programming Language :: Python :: Implementation :: CPython
Classifier: Programming Language :: Python :: Implementation :: PyPy
Requires-Python: >=3.7.1
